Metadata-Version: 2.1
Name: odoo12-addon-stock-barcodes
Version: 12.0.2.3.0
Summary: It provides read barcode on stock operations.
Home-page: https://github.com/OCA/stock-logistics-barcode
Author: Tecnativa, Odoo Community Association (OCA)
Author-email: support@odoo-community.org
License: AGPL-3
Platform: UNKNOWN
Classifier: Programming Language :: Python
Classifier: Framework :: Odoo
Classifier: Framework :: Odoo :: 12.0
Classifier: License :: OSI Approved :: GNU Affero General Public License v3
Requires-Python: >=3.5
Requires-Dist: odoo (<12.1dev,>=12.0a)
